sdpa_python-0.2.2.dist-info/RECORD
sdpa_python-0.2.2.dist-info/LICENSE
sdpa_python-0.2.2.dist-info/WHEEL
sdpa_python-0.2.2.dist-info/top_level.txt
sdpa_python-0.2.2.dist-info/METADATA
sdpap/sdpap.py
sdpap/convert.py
sdpap/__init__.py
sdpap/param.py
sdpap/symcone.py
sdpap/matdata.py
sdpap/sdpaputils.py
sdpap/fileio.py
sdpap/spcolo/spcoloext.cpython-311-darwin.so
sdpap/spcolo/clique.py
sdpap/spcolo/__init__.py
sdpap/spcolo/asputils.py
sdpap/spcolo/spcolo.py
sdpap/sdpacall/__init__.py
sdpap/sdpacall/sdpa.cpython-311-darwin.so
sdpap/sdpacall/sdpacall.py
sdpap/.dylibs/libstdc++.6.dylib
sdpap/.dylibs/libgcc_s.1.1.dylib
sdpap/fvelim/__init__.py
sdpap/fvelim/fvelim.py
sdpap/fvelim/fvelimext.cpython-311-darwin.so
