Metadata-Version: 2.1
Name: sdpa-python
Version: 0.2.2
Summary: SDPA (SemiDefinite Programming Algorithm) for Python
Home-page: https://sdpa-python.github.io
Maintainer: Usama Muneeb
Maintainer-email: umunee2@uic.edu
License: GNU GPL version 2
Classifier: Development Status :: 3 - Alpha
Classifier: Intended Audience :: Science/Research
Classifier: License :: OSI Approved :: GNU General Public License v2 (GPLv2)
Classifier: Operating System :: OS Independent
Classifier: Topic :: Scientific/Engineering
Requires-Python: >=3.7
License-File: LICENSE
Requires-Dist: scipy >=1.1.0
